__init__.py
__version__.py
add_toc.py
ds_utils.py
ml_utils.py
dsx/__init__.py
dsx/__version__.py
dsx/add_toc.py
dsx/ds_utils.py
dsx/logging.py
dsx/ml_utils.py
dsx-0.9.11.dist-info/LICENSE.txt
dsx-0.9.11.dist-info/METADATA
dsx-0.9.11.dist-info/WHEEL
dsx-0.9.11.dist-info/entry_points.txt
dsx-0.9.11.dist-info/top_level.txt
dsx-0.9.11.dist-info/RECORD
