Metadata-Version: 2.1
Name: dsx
Version: 0.9.11
Summary: The utilities pack for data science and analytics tasks.
Author-email: NicTsyen <nic.tsyen@outlook.com>
Project-URL: homepage, https://github.com/NicTsyen/dsx
Project-URL: documentation, https://dataninja.ml/data-analytics/dsx
Project-URL: repository, https://github.com/NicTsyen/dsx
Keywords: pandas,utility
Classifier: License :: OSI Approved :: MIT License
Classifier: Programming Language :: Python
Classifier: Programming Language :: Python :: 3
Requires-Python: >=3.10
License-File: LICENSE.txt
Requires-Dist: joblib
Requires-Dist: seaborn
Requires-Dist: pandas
Requires-Dist: numpy
Requires-Dist: scipy
Requires-Dist: matplotlib
Requires-Dist: regex
Provides-Extra: dev
Requires-Dist: shutil ; extra == 'dev'
Requires-Dist: xlsxwriter ; extra == 'dev'
Requires-Dist: openpyxl ; extra == 'dev'
